pyangexcel/__init__.py
pyangexcel/excel.py
pyangexcel-0.4.dist-info/LICENSE
pyangexcel-0.4.dist-info/METADATA
pyangexcel-0.4.dist-info/WHEEL
pyangexcel-0.4.dist-info/top_level.txt
pyangexcel-0.4.dist-info/RECORD
