Metadata-Version: 2.1
Name: pyangexcel
Version: 0.4
Summary: A pyang excel plugin to produce a Excel Schema file
Home-page: https://github.com/neoul/pyangexcel
Author: neoul
Author-email: neoul@ymail.com
License: Apache License
Keywords: pyang,yang
Platform: UNKNOWN
Requires-Dist: openpyxl
Requires-Dist: pyang
